MongodbJiaochengCYuyanBianchengWangFix1/README.md
MongodbJiaochengCYuyanBianchengWangFix1/__init__.py
MongodbJiaochengCYuyanBianchengWangFix1/__main__.py
MongodbJiaochengCYuyanBianchengWangFix1/file.epub
MongodbJiaochengCYuyanBianchengWangFix1/index.html
MongodbJiaochengCYuyanBianchengWangFix1/css/__init__.py
MongodbJiaochengCYuyanBianchengWangFix1/css/annotations.css
MongodbJiaochengCYuyanBianchengWangFix1/css/main.css
MongodbJiaochengCYuyanBianchengWangFix1/css/normalize.css
MongodbJiaochengCYuyanBianchengWangFix1/css/popup.css
MongodbJiaochengCYuyanBianchengWangFix1/font/__init__.py
MongodbJiaochengCYuyanBianchengWangFix1/font/fontello.eot
MongodbJiaochengCYuyanBianchengWangFix1/font/fontello.svg
MongodbJiaochengCYuyanBianchengWangFix1/font/fontello.ttf
MongodbJiaochengCYuyanBianchengWangFix1/font/fontello.woff
MongodbJiaochengCYuyanBianchengWangFix1/img/__init__.py
MongodbJiaochengCYuyanBianchengWangFix1/img/annotator-glyph-sprite.png
MongodbJiaochengCYuyanBianchengWangFix1/img/annotator-icon-sprite.png
MongodbJiaochengCYuyanBianchengWangFix1/img/apple-touch-icon.png
MongodbJiaochengCYuyanBianchengWangFix1/img/cancelfullscreen.png
MongodbJiaochengCYuyanBianchengWangFix1/img/close.png
MongodbJiaochengCYuyanBianchengWangFix1/img/fullscreen.png
MongodbJiaochengCYuyanBianchengWangFix1/img/loader.gif
MongodbJiaochengCYuyanBianchengWangFix1/img/menu-icon.png
MongodbJiaochengCYuyanBianchengWangFix1/img/save.png
MongodbJiaochengCYuyanBianchengWangFix1/img/saved.png
MongodbJiaochengCYuyanBianchengWangFix1/img/settings-s.png
MongodbJiaochengCYuyanBianchengWangFix1/img/settings.png
MongodbJiaochengCYuyanBianchengWangFix1/img/star.png
MongodbJiaochengCYuyanBianchengWangFix1/js/__init__.py
MongodbJiaochengCYuyanBianchengWangFix1/js/epub.js
MongodbJiaochengCYuyanBianchengWangFix1/js/epub.min.js
MongodbJiaochengCYuyanBianchengWangFix1/js/epub.min.map
MongodbJiaochengCYuyanBianchengWangFix1/js/hooks.min.js
MongodbJiaochengCYuyanBianchengWangFix1/js/hooks.min.map
mongodb_jiaocheng_c_yuyan_biancheng_wang_fix1-2025.3.24.1.dist-info/METADATA
mongodb_jiaocheng_c_yuyan_biancheng_wang_fix1-2025.3.24.1.dist-info/WHEEL
mongodb_jiaocheng_c_yuyan_biancheng_wang_fix1-2025.3.24.1.dist-info/entry_points.txt
mongodb_jiaocheng_c_yuyan_biancheng_wang_fix1-2025.3.24.1.dist-info/top_level.txt
mongodb_jiaocheng_c_yuyan_biancheng_wang_fix1-2025.3.24.1.dist-info/RECORD
